{
  "data": {
    "data": {
      "order": {
        "id": 914048205,
        "type": "pickup",
        "merchantRefId": null,
        "deliveryDate": "2025-07-24 08:40:10",
        "created": "2025-07-24 08:30:13",
        "updated": "2025-07-24 09:40:00",
        "timeSlotStart": null,
        "timeSlotEnd": null,
        "discount": 0.0,
        "totalTaxes": 0.1,
        "totalCharges": 0.0,
        "subtotal": 1.49,
        "payableAmount": 1.59,
        "walletCreditApplied": 0.0,
        "paymentMode": "PAYMENT_GATEWAY",
        "channel": "PHONEORDER",
        "channelLogo": "https://cdn.urbanpiper.com/media/platforms/images.jpeg",
        "status": "EXPIRED",
        "instructions": "",
        "nextStates": [],
        "nextState": null,
        "couponText": null,
        "aggregatorPayload": null,
        "externalPlatform": {
          "id": "239833",
          "deliveryType": "SELF",
          "bizPlatform": {
            "platform": {
              "name": "phoneorder",
              "__typename": "OrderingPlatformType"
            },
            "__typename": "BizOrderingPlatformType"
          },
          "__typename": "PlatformOrderType"
        },
        "taxes": [],
        "charges": [],
        "address": {
          "id": null,
          "name": "",
          "address1": "",
          "address2": "",
          "city": "NA",
          "pin": "NA",
          "subLocality": "NA",
          "__typename": "OrderAddressType"
        },
        "store": {
          "title": "Union NJ",
          "brand": null,
          "__typename": "BizLocationType"
        },
        "customer": {
          "id": 47501855,
          "firstName": "Jack",
          "lastName": "",
          "phone": "+917240298957",
          "email": "",
          "__typename": "CustomerType"
        },
        "items": [
          {
            "id": 5496120,
            "title": "Single Bagel",
            "price": 1.49,
            "quantity": 1,
            "totalCharge": 0.0,
            "totalTax": 0.1,
            "total": 1.59,
            "discount": 0.0,
            "discountCode": null,
            "instructions": null,
            "taxes": [
              {
                "id": "4337500344",
                "title": "Tax",
                "value": 0.1,
                "rate": 6.625,
                "__typename": "BillComponentValueType"
              }
            ],
            "charges": [],
            "optionsToAdd": [
              {
                "id": "5709136",
                "title": "Plain",
                "price": "0.0",
                "priceAtLocation": 0.0,
                "weight": null,
                "description": "",
                "__typename": "BizItemOptionType"
              }
            ],
            "orderItemOptions": [
              {
                "id": 5709136,
                "quantity": 1,
                "__typename": "OrderItemOptionsType"
              }
            ],
            "__typename": "OrderItemType"
          }
        ],
        "statusUpdates": [
          {
            "id": "4359304779",
            "status": "AWAITING_PAYMENT",
            "prevStatus": null,
            "message": "Online payment. Txn ID=up_txn_a61ba4d15c3f. Value=0.0159",
            "updatedBy": null,
            "created": "2025-07-24 08:30:13",
            "__typename": "OrderStatusUpdateType"
          }
        ],
        "delivery": null,
        "paymentTransaction": {
          "txnId": "up_txn_a61ba4d15c3f",
          "amount": 1,
          "gwTxnId": "pi_3RoOHoRt38BwTo290Y8AA078",
          "state": "initialized",
          "comments": "",
          "history": "[{\"state\": \"initialized\", \"comments\": [{\"msg\": \"initiated - 2025-07-24 | 12:30:11\", \"extra_details\": {}}]}]",
          "paymentMethod": null,
          "__typename": "PaymentTransactionType"
        },
        "parentOrder": null,
        "childOrderId": null,
        "__typename": "OrderType"
      }
    }
  }
}