{
  "data": {
    "data": {
      "order": {
        "id": 916974899,
        "type": "pickup",
        "merchantRefId": null,
        "deliveryDate": "2025-07-27 14:23:24",
        "created": "2025-07-27 14:13:26",
        "updated": "2025-07-27 15:20:00",
        "timeSlotStart": null,
        "timeSlotEnd": null,
        "discount": 0.0,
        "totalTaxes": 0.76,
        "totalCharges": 0.0,
        "subtotal": 11.48,
        "payableAmount": 12.24,
        "walletCreditApplied": 0.0,
        "paymentMode": "PAYMENT_GATEWAY",
        "channel": "PHONEORDER",
        "channelLogo": "https://cdn.urbanpiper.com/media/platforms/images.jpeg",
        "status": "EXPIRED",
        "instructions": "none",
        "nextStates": [],
        "nextState": null,
        "couponText": null,
        "aggregatorPayload": null,
        "externalPlatform": {
          "id": "610250",
          "deliveryType": "SELF",
          "bizPlatform": {
            "platform": {
              "name": "phoneorder",
              "__typename": "OrderingPlatformType"
            },
            "__typename": "BizOrderingPlatformType"
          },
          "__typename": "PlatformOrderType"
        },
        "taxes": [],
        "charges": [],
        "address": {
          "id": null,
          "name": "",
          "address1": "",
          "address2": "",
          "city": "NA",
          "pin": "NA",
          "subLocality": "NA",
          "__typename": "OrderAddressType"
        },
        "store": {
          "title": "Union NJ",
          "brand": null,
          "__typename": "BizLocationType"
        },
        "customer": {
          "id": 47395752,
          "firstName": "Quibble",
          "lastName": "",
          "phone": "+919780032269",
          "email": "",
          "__typename": "CustomerType"
        },
        "items": [
          {
            "id": 5496184,
            "title": "Small Hot Chocolate (12oz)",
            "price": 4.49,
            "quantity": 1,
            "totalCharge": 0.0,
            "totalTax": 0.3,
            "total": 4.79,
            "discount": 0.0,
            "discountCode": null,
            "instructions": null,
            "taxes": [
              {
                "id": "4351888889",
                "title": "Tax",
                "value": 0.3,
                "rate": 6.625,
                "__typename": "BillComponentValueType"
              }
            ],
            "charges": [],
            "optionsToAdd": [
              {
                "id": "5709690",
                "title": "Medium 16oz",
                "price": "4.49",
                "priceAtLocation": 4.49,
                "weight": null,
                "description": "",
                "__typename": "BizItemOptionType"
              }
            ],
            "orderItemOptions": [
              {
                "id": 5709690,
                "quantity": 1,
                "__typename": "OrderItemOptionsType"
              }
            ],
            "__typename": "OrderItemType"
          },
          {
            "id": 5496113,
            "title": "Egg & Cheese",
            "price": 6.99,
            "quantity": 1,
            "totalCharge": 0.0,
            "totalTax": 0.46,
            "total": 7.45,
            "discount": 0.0,
            "discountCode": null,
            "instructions": null,
            "taxes": [
              {
                "id": "4351888890",
                "title": "Tax",
                "value": 0.46,
                "rate": 6.625,
                "__typename": "BillComponentValueType"
              }
            ],
            "charges": [],
            "optionsToAdd": [
              {
                "id": "5709036",
                "title": "Rainbow Bagel",
                "price": "1.0",
                "priceAtLocation": 1.0,
                "weight": null,
                "description": "",
                "__typename": "BizItemOptionType"
              },
              {
                "id": "5709067",
                "title": "Lightly Toasted",
                "price": "0.0",
                "priceAtLocation": 0.0,
                "weight": null,
                "description": "",
                "__typename": "BizItemOptionType"
              },
              {
                "id": "5709076",
                "title": "Butter",
                "price": "1.0",
                "priceAtLocation": 1.0,
                "weight": null,
                "description": "",
                "__typename": "BizItemOptionType"
              },
              {
                "id": "5709092",
                "title": "Scrambled",
                "price": "0.0",
                "priceAtLocation": 0.0,
                "weight": null,
                "description": "",
                "__typename": "BizItemOptionType"
              }
            ],
            "orderItemOptions": [
              {
                "id": 5709036,
                "quantity": 1,
                "__typename": "OrderItemOptionsType"
              },
              {
                "id": 5709067,
                "quantity": 1,
                "__typename": "OrderItemOptionsType"
              },
              {
                "id": 5709092,
                "quantity": 1,
                "__typename": "OrderItemOptionsType"
              },
              {
                "id": 5709076,
                "quantity": 1,
                "__typename": "OrderItemOptionsType"
              }
            ],
            "__typename": "OrderItemType"
          }
        ],
        "statusUpdates": [
          {
            "id": "4372995395",
            "status": "AWAITING_PAYMENT",
            "prevStatus": null,
            "message": "Online payment. Txn ID=up_txn_ac9340f72ee1. Value=0.1224",
            "updatedBy": null,
            "created": "2025-07-27 14:13:26",
            "__typename": "OrderStatusUpdateType"
          }
        ],
        "delivery": null,
        "paymentTransaction": {
          "txnId": "up_txn_ac9340f72ee1",
          "amount": 12,
          "gwTxnId": "pi_3RpZ4bRt38BwTo290KupF4vf",
          "state": "initialized",
          "comments": "",
          "history": "[{\"state\": \"initialized\", \"comments\": [{\"msg\": \"initiated - 2025-07-27 | 18:13:24\", \"extra_details\": {}}]}]",
          "paymentMethod": null,
          "__typename": "PaymentTransactionType"
        },
        "parentOrder": null,
        "childOrderId": null,
        "__typename": "OrderType"
      }
    }
  }
}